{"controlador.ed.lista.ListaEnlazada":{"cabecera":{"info":{"@class":"modelo.Sucursal","id":0,"nombre":"a","ventas":{"cabecera":{"info":{"@class":"modelo.Venta","id":0,"valor":5000,"mes":"ENERO"},"sig":{"info":{"@class":"modelo.Venta","id":1,"valor":20,"mes":"FEBRERO"},"sig":{"info":{"@class":"modelo.Venta","id":2,"valor":0,"mes":"MARZO"},"sig":{"info":{"@class":"modelo.Venta","id":3,"valor":0,"mes":"ABRIL"},"sig":{"info":{"@class":"modelo.Venta","id":4,"valor":0,"mes":"MAYO"},"sig":{"info":{"@class":"modelo.Venta","id":5,"valor":0,"mes":"JUNIO"},"sig":{"info":{"@class":"modelo.Venta","id":6,"valor":0,"mes":"JULIO"},"sig":{"info":{"@class":"modelo.Venta","id":7,"valor":0,"mes":"AGOSTO"},"sig":{"info":{"@class":"modelo.Venta","id":8,"valor":0,"mes":"SEPTIEMBRE"},"sig":{"info":{"@class":"modelo.Venta","id":9,"valor":0,"mes":"OCTUBRE"},"sig":{"info":{"@class":"modelo.Venta","id":10,"valor":0,"mes":"NOVIEMBRE"},"sig":{"info":{"@class":"modelo.Venta","id":11,"valor":0,"mes":"DICIEMBRE"}}}}}}}}}}}}},"size":12}},"sig":{"info":{"@class":"modelo.Sucursal","id":1,"nombre":"b","ventas":{"size":0}}}},"size":2}}